parsac/__init__.py
parsac/core.py
parsac/record.py
parsac/util.py
parsac/job/__init__.py
parsac/job/gotm.py
parsac/optimize/__init__.py
parsac/optimize/desolver.py
parsac/optimize/plot.py
parsac/sensitivity/__init__.py
parsac-2.1.2.dist-info/METADATA
parsac-2.1.2.dist-info/WHEEL
parsac-2.1.2.dist-info/licenses/LICENSE
parsac-2.1.2.dist-info/RECORD
