Metadata-Version: 2.4
Name: parsac
Version: 2.1.2
Summary: Parallel Sensitivity Analysis and Calibration
Project-URL: homepage, https://github.com/BoldingBruggeman/parsac
Project-URL: documentation, https://parsac.readthedocs.io/
Author-email: Jorn Bruggeman <jorn@bolding-bruggeman.com>
License-File: LICENSE
Classifier: Development Status :: 4 - Beta
Classifier: Intended Audience :: Science/Research
Classifier: License :: OSI Approved :: GNU General Public License (GPL)
Classifier: Operating System :: OS Independent
Classifier: Programming Language :: Python :: 3
Classifier: Topic :: Scientific/Engineering
Requires-Python: >=3.9
